{
  "project_info": {
    "project_number": "983799095293",
    "project_id": "flutter-chat-app-23b1d",
    "storage_bucket": "flutter-chat-app-23b1d.firebasestorage.app"
  },
  "client": [
    {
      "client_info": {
        "mobilesdk_app_id": "1:983799095293:android:e243b1d10d8dbdc30f0394",
        "android_client_info": {
          "package_name": "com.example.chat_app"
        }
      },
      "oauth_client": [],
      "api_key": [
        {
          "current_key": "AIzaSyA9W4Ro_e6In7G-vEsYiEKrWcnsMjGA4Hc"
        }
      ],
      "services": {
        "appinvite_service": {
          "other_platform_oauth_client": []
        }
      }
    }
  ],
  "configuration_version": "1"
}